apyds_bnf/.gitignore
apyds_bnf/DsLexer.py
apyds_bnf/DsParser.py
apyds_bnf/DsVisitor.py
apyds_bnf/DspLexer.py
apyds_bnf/DspParser.py
apyds_bnf/DspVisitor.py
apyds_bnf/__init__.py
apyds_bnf/py.typed
apyds_bnf-0.0.14.dist-info/METADATA
apyds_bnf-0.0.14.dist-info/WHEEL
apyds_bnf-0.0.14.dist-info/top_level.txt
apyds_bnf-0.0.14.dist-info/RECORD
