Metadata-Version: 2.4
Name: apyds-bnf
Version: 0.0.14
Summary: BNF parser and unparsers for DS - conversion between lisp-like and traditional syntax
Author-email: Hao Zhang <hzhangxyz@outlook.com>
License-Expression: AGPL-3.0-or-later
Project-URL: Repository, https://github.com/USTC-KnowledgeComputingLab/ds.git
Requires-Python: <3.15,>=3.11
Requires-Dist: antlr4-python3-runtime~=4.13.2
Provides-Extra: dev
Requires-Dist: ruff~=0.14.10; extra == "dev"
Requires-Dist: pytest~=9.0.2; extra == "dev"
Requires-Dist: pytest-cov~=7.0.0; extra == "dev"
